scout_api/__init__.py
scout_api/scout_api.py
scout_api/version.py
scout_api-0.1.0.data/scripts/scout-api
scout_api-0.1.0.dist-info/DESCRIPTION.rst
scout_api-0.1.0.dist-info/METADATA
scout_api-0.1.0.dist-info/metadata.json
scout_api-0.1.0.dist-info/RECORD
scout_api-0.1.0.dist-info/top_level.txt
scout_api-0.1.0.dist-info/WHEEL
